Workbook

Sheet Index
D3: 1 | E3: Login Credentials (URL, User, Password, PIN)
D4: 2 | E4: SBI Securities (Tracking, Sell, Buy)
D5: 3 | E5: Mutual Funds
F6: India
F7: Japan
D8: 4 | E8: Ricardo`s Demise
D9: 5 | E9: Kaori`s Demise
D10: 6 | E10: Tanaka Kikinzoku
D11: 7 | E11: Crypto Currency
F12: Current Assets
F13: Wallets
F14: Buy and Sell
F15: Educational Videos
D16: 8 | E16: NRO, NRE
D17: 9 | E17: Tenant Information
F18: India
F19: Japan
D20: 10 | E20: Banks, Cash
D21: 11 | E21: Physical Gold India
D22: 12 | E22: Life Insurance Policies
F23: India
F24: Japan
D25: 13 | E25: Fixed Deposits
D26: 14 | E26: Passive Income
D27: 15 | E27: Real Estate
F28: India
F29: Japan
D30: 16 | E30: Stamps
D31: 17 | E31: Loans
F32: Taken
F33: Given
D34: 18 | E34: NISA
F35: Old Nisa
F36: New Nisa
F37: Tsumitate Nisa
D38: 19 | E38: Japanese Pension (年金）
D39: 20 | E39: Souzokuzei (相続税)
D40: 21 | E40: Global Assets
F41: Summary
F42: Details

Sheet Global Assets (2)
A1: As on 22-4-2026
B2: Real estate | I2: 1 USD | J2: 159.5 | K2: JPY
C3: India | I3: 1 USD | J3: 93.8 | K3: INR
D4: Current Sale Price | E4: Flat | F4: INR | G4: JPY | H4: USD | I4: 1 INR | J4: 1.7 | K4: JPY
E5: Poonam Residency | F5: 10500000 | G5: =F5*J4 -> 17850000 | H5: =F5/J3 -> 111940.3
E6: Sunway Megapolis | F6: 8500000 | G6: =F6*J4 -> 14450000 | H6: =F6/J3 -> 90618.337
E7: Osia Maple Leaf | F7: 7500000 | G7: =F7*J4 -> 12750000 | H7: =F7/J3 -> 79957.356
E8: Venusta Classic | F8: 5500000 | G8: =F8*J4 -> 9350000 | H8: =F8/J3 -> 58635.394
E9: Altamonte | F9: 4500000 | G9: =F9*J4 -> 7650000 | H9: =F9/J3 -> 47974.414
E10: Osia Arcade | F10: 2000000 | G10: =F10*J4 -> 3400000 | H10: =F10/J3 -> 21321.962
E11: Total | F11: =SUM(F5:F10) -> 38500000 | G11: =SUM(G5:G10) -> 65450000 | H11: =SUM(H5:H10) -> 410447.76
C12: Japan
D13: Capital repayment | E13: Flat | F13: JPY | G13: INR | H13: USD | I13: Purchase Amt JPY
E14: Ober Grandious | F14: 12781330 | G14: =F14/J4 -> 7518429.4 | H14: =F14/J2 -> 80133.73 | I14: 38000000
E15: Phoenix Waseda | F15: 3400750 | G15: =F15/J4 -> 2000441.2 | H15: =F15/J2 -> 21321.317 | I15: 15000000
E16: Urban Hills Waseda | F16: 2952420 | G16: =F16/J4 -> 1736717.6 | H16: =F16/J2 -> 18510.47 | I16: 13500000
E17: Lions Plaza Hakusan | F17: 2140772 | G17: =F17/J4 -> 1259277.6 | H17: =F17/J2 -> 13421.768 | I17: 11000000
E18: Castle mansion | F18: 2294411 | G18: =F18/J4 -> 1349653.5 | H18: =F18/J2 -> 14385.022 | I18: 13500000
E19: Total | F19: =SUM(F13:F18) -> 23569683 | G19: =SUM(G13:G18) -> 13864519 | H19: =SUM(H13:H18) -> 147772.31 | I19: =SUM(I13:I18) -> 91000000 | J19: =I19-F19 -> 67430317
D21: Current Sale Price | E21: Flat | F21: Purchase Price JPY | G21: Sale Price JPY | H21: Unrealized Profit JPY | I21: INR | J21: USD
E22: Ober Grandious | F22: 38000000 | G22: =F22*0.3 + F22 -> 49400000 | H22: =G22-F22 -> 11400000 | I22: =H22*J4 -> 19380000 | J22: =H22/J3 -> 121535.18
E23: Phoenix Waseda | F23: 15000000 | G23: =F23*0.3 + F23 -> 19500000 | H23: =G23-F23 -> 4500000 | I23: =H23*J4 -> 7650000 | J23: =H23/J3 -> 47974.414
E24: Urban Hills Waseda | F24: 13500000 | G24: =F24*0.3 + F24 -> 17550000 | H24: =G24-F24 -> 4050000 | I24: =H24*J4 -> 6885000 | J24: =H24/J3 -> 43176.972
E25: Lions Plaza Hakusan | F25: 11000000 | G25: =F25*0.3 + F25 -> 14300000 | H25: =G25-F25 -> 3300000 | I25: =H25*J4 -> 5610000 | J25: =H25/J3 -> 35181.237
E26: Castle mansion | F26: 13500000 | G26: =F26*0.3 + F26 -> 17550000 | H26: =G26-F26 -> 4050000 | I26: =H26*J4 -> 6885000 | J26: =H26/J3 -> 43176.972
E27: Total | F27: =SUM(F22:F26) -> 91000000 | G27: =SUM(G22:G26) -> 118300000 | H27: =SUM(H22:H26) -> 27300000 | I27: =SUM(I22:I26) -> 46410000 | J27: =SUM(J22:J26) -> 291044.78
D30: Capital repayment + Unrealized Profit
E31: Flat | F31: Profit JPY | G31: INR | H31: USD
E32: Ober Grandious | F32: =H22+F14 -> 24181330 | G32: =F32/J4 -> 14224312 | H32: =G32/J3 -> 151645.11
E33: Phoenix Waseda | F33: =H23+F15 -> 7900750 | G33: =F33/J4 -> 4647500 | H33: =G33/J3 -> 49546.908
E34: Urban Hills Waseda | F34: =H24+F16 -> 7002420 | G34: =F34/J4 -> 4119070.6 | H34: =G34/J3 -> 43913.332
E35: Lions Plaza Hakusan | F35: =H25+F17 -> 5440772 | G35: =F35/J4 -> 3200454.1 | H35: =G35/J3 -> 34119.98
E36: Castle mansion | F36: =H26+F18 -> 6344411 | G36: =F36/J4 -> 3732006.5 | H36: =G36/J3 -> 39786.849
E37: Total | F37: =SUM(F32:F36) -> 50869683 | G37: =SUM(G32:G36) -> 29923343 | H37: =SUM(H32:H36) -> 319012.18
B41: Cash
C42: India
D43: Fixed Deposits
E44: Bank | F44: USD | G44: INR | H44: JPY
E45: State Bank of India | F45: 292018 | G45: =F45*J3 -> 27391288 | H45: =F45*J2 -> 46576871
E46: State Bank of India | F46: 5070 | G46: =F46*J3 -> 475566 | H46: =F46*J2 -> 808665
E47: Bank of India | F47: 90991 | G47: =F47*J3 -> 8534955.8 | H47: =F47*J2 -> 14513064
E48: Bank of India | F48: 2351 | G48: =F48*J4 -> 3996.7 | H48: =F48*J3 -> 220523.8
E49: HDFC Bank | F49: 17000 | G49: =F49*J3 -> 1594600 | H49: =F49*J2 -> 2711500
E50: Bank of Baroda | F50: =G50/J3 -> 4690.8316 | G50: 440000 | H50: =F50*J2 -> 748187.63
E51: Yes Bank | F51: =G51/J3 -> 884.86141 | G51: 83000 | H51: =F51*J2 -> 141135.39
E52: Total | F52: =SUM(F44:F49) -> 407430 | G52: =SUM(G44:G49) -> 38000407 | H52: =SUM(H44:H49) -> 64830624
D54: Cash in Hand
E55: Bank | F55: NRE INR | G55: NRO INR | H55: NRO + NRE INR | I55: JPY | J55: USD
D56: Ricardo | E56: State Bank of India | F56: 10280 | G56: 510255 | H56: =F56+G56 -> 520535 | I56: =H56*J4 -> 884909.5 | J56: =I56/J2 -> 5548.0219
E57: Bank of India | F57: 5004 | G57: 2141703 | H57: =F57+G57 -> 2146707 | I57: =H57*J4 -> 3649401.9 | J57: =I57/J2 -> 22880.263
E58: ICICI Bank | F58: 0 | G58: 3940478 | H58: =F58+G58 -> 3940478 | I58: =H58*J4 -> 6698812.6 | J58: =I58/J2 -> 41998.825
E59: Bank of Baroda | F59: 0 | G59: 30000 | H59: =F59+G59 -> 30000 | I59: =H59*J4 -> 51000 | J59: =I59/J2 -> 319.74922
E60: HDFC Bank | F60: 0 | G60: 15000 | H60: =F60+G60 -> 15000 | I60: =H60*J4 -> 25500 | J60: =I60/J2 -> 159.87461
E61: Yes Bank | F61: 10000 | G61: 10000 | H61: =F61+G61 -> 20000 | I61: =H61*J4 -> 34000 | J61: =I61/J2 -> 213.16614
E62: Total | F62: =SUM(F56:F61) -> 25284 | G62: =SUM(G56:G61) -> 6647436 | H62: =SUM(H56:H61) -> 6672720 | I62: =SUM(I56:I61) -> 11343624 | J62: =SUM(J56:J61) -> 71119.9
F63: INR | G63: JPY | H63: USD
D64: Mom | E64: State Bank of India | F64: 0 | G64: =F64*J4 -> 0 | H64: =G64/J2 -> 0
E65: ICICI Bank | F65: 755193 | G65: =F65*J4 -> 1283828.1 | H65: =G65/J2 -> 8049.079
E66: Bank of Baroda | F66: 152000 | G66: =F66*J4 -> 258400 | H66: =G66/J2 -> 1620.0627
E67: Punjab National | F67: 0 | G67: =F67*J4 -> 0 | H67: =G67/J2 -> 0
E68: Post Office | F68: 0 | G68: =F68*J4 -> 0 | H68: =G68/J2 -> 0
E69: Total | F69: =SUM(F62:F66) -> 932477 | G69: =SUM(G64:G68) -> 1542228.1 | H69: =SUM(H64:H68) -> 9669.1417
F71: INR | G71: JPY | H71: USD
D72: Bong | E72: ICICI Bank | F72: 160000 | G72: =F72*J4 -> 272000 | H72: =F72/J3 -> 1705.7569
E73: Total | F73: =F72 -> 160000 | G73: =G72 -> 272000 | H73: =H72 -> 1705.7569
F75: INR | G75: JPY | H75: USD
D76: Paul | E76: Yes Bank | F76: 0 | G76: =F76*J4 -> 0 | H76: =F76/J3 -> 0
E77: Total | F77: =F76 -> 0 | G77: =G76 -> 0 | H77: =H76 -> 0
D79: Grand Total India | F79: INR | G79: JPY | H79: USD
F80: =G52+H62+F69+F73+F77 -> 45765604 | G80: =H52+I62+G69+G73+G77 -> 77988476 | H80: =F52+J62+H69+H73+H77 -> 489924.8
C88: Japan
D89: Cash in Hand and Bank
E90: Bank | F90: JPY | G90: INR | H90: USD
D91: Ricardo | E91: Shinsei | F91: 2309803 | G91: =F91/J4 -> 1358707.6 | H91: =F91/J2 -> 14481.524
E92: Post Office | F92: 699722 | G92: =F92/J4 -> 411601.18 | H92: =F92/J2 -> 4386.9718
E93: 7-Eleven | F93: 200308 | G93: =F93/J4 -> 117828.24 | H93: =F93/J2 -> 1255.8495
E94: MUFJ | F94: 200185 | G94: =F94/J4 -> 117755.88 | H94: =F94/J2 -> 1255.0784
E95: Mizuho | F95: 200682 | G95: =F95/J4 -> 118048.24 | H95: =F95/J2 -> 1258.1944
E96: SMBC | F96: 50458 | G96: =F96/J4 -> 29681.176 | H96: =F96/J2 -> 316.3511
E97: Japan Netto | F97: 250175 | G97: =F97/J4 -> 147161.76 | H97: =F97/J2 -> 1568.4953
E98: Rakuten | F98: 200316 | G98: =F98/J4 -> 117832.94 | H98: =F98/J2 -> 1255.8997
E99: Total | F99: =SUM(F91:F98) -> 4111649 | G99: =SUM(G91:G98) -> 2418617.1 | H99: =SUM(H91:H98) -> 25778.364
E101: Bank | F101: JPY | G101: INR | H101: USD
D102: Kaori | E102: Mizuho | F102: 1954124 | G102: =F102/J4 -> 1149484.7 | H102: =F102/J2 -> 12251.561
E103: MUFJ | F103: 405710 | G103: =F103/J4 -> 238652.94 | H103: =F103/J2 -> 2543.6364
E104: Post Office | F104: 290907 | G104: =F104/J4 -> 171121.76 | H104: =F104/J2 -> 1823.8683
E105: Shinsei | F105: 450310 | G105: =F105/J4 -> 264888.24 | H105: =F105/J2 -> 2823.2602
E106: Rakuten | F106: 40000 | G106: =F106/J4 -> 23529.412 | H106: =F106/J2 -> 250.7837
E107: Total | F107: =SUM(F102:F106) -> 3141051 | G107: =SUM(G102:G106) -> 1847677.1 | H107: =SUM(H102:H106) -> 19693.11
E109: Expenses | F109: JPY | G109: INR | H109: USD
D110: Cash in Envelope 2026 | E110: AU Pay Suica | F110: 600000 | G110: =F110/J4 -> 352941.18 | H110: =F110/J2 -> 3761.7555
E111: Nenkin Kenkohoken | F111: 350000 | G111: =F111/J4 -> 205882.35 | H111: =F111/J2 -> 2194.3574
E112: Minimaid Travel | F112: 190000 | G112: =F112/J4 -> 111764.71 | H112: =F112/J2 -> 1191.2226
E113: Kotei Shisanzei | F113: 260000 | G113: =F113/J4 -> 152941.18 | H113: =F113/J2 -> 1630.094
E114: Kaatsu Pilates | F114: 290000 | G114: =F114/J4 -> 170588.24 | H114: =F114/J2 -> 1818.1818
E115: Okozukai | F115: 100000 | G115: =F115/J4 -> 58823.529 | H115: =F115/J2 -> 626.95925
E116: Total | F116: =SUM(F110:F115) -> 1790000 | G116: =SUM(G110:G115) -> 1052941.2 | H116: =SUM(H110:H115) -> 11222.571
E118: Expenses | F118: JPY | G118: INR | H118: USD
D119: Cash in Envelope 2027 | E119: Not decided | F119: 350000 | G119: =F119/J4 -> 205882.35 | H119: =F119/J2 -> 2194.3574
E120: Total | F120: =SUM(F119:F119) -> 350000 | G120: =SUM(G119:G119) -> 205882.35 | H120: =SUM(H119:H119) -> 2194.3574
...

Sheet Global Assets
A2: Region | B2: Asset Category | C2: Asset Owner | D2: Asset | E2: INR | F2: USD | G2: JPY
A3: India | B3: Real estate | C3: Ricardo | D3: Poonam Residency | E3: 10500000 | F3: =E3/Formula!B3 -> 111940.3 | G3: =E3*Formula!B4 -> 17850000
A4: - | B4: - | C4: - | D4: Sunway Megapolis | E4: 8500000 | F4: =E4/Formula!B3 -> 90618.337 | G4: =E4*Formula!B4 -> 14450000
A5: - | B5: - | C5: - | D5: Osia Maple Leaf | E5: 7500000 | F5: =E5/Formula!B3 -> 79957.356 | G5: =E5*Formula!B4 -> 12750000
A6: - | B6: - | C6: - | D6: Venusta Classic | E6: 5500000 | F6: =E6/Formula!B3 -> 58635.394 | G6: =E6*Formula!B4 -> 9350000
A7: - | B7: - | C7: - | D7: Altamonte | E7: 4500000 | F7: =E7/Formula!B3 -> 47974.414 | G7: =E7*Formula!B4 -> 7650000
A8: - | B8: - | C8: - | D8: Osia Arcade | E8: 2000000 | F8: =E8/Formula!B3 -> 21321.962 | G8: =E8*Formula!B4 -> 3400000
A9: India | B9: Fixed Deposits | C9: Ricardo | D9: State Bank of India | E9: =F9*Formula!B3 -> 27391288 | F9: 292018 | G9: =F9*Formula!B2 -> 46576871
A10: - | B10: - | C10: - | D10: State Bank of India | E10: =F10*Formula!B3 -> 475566 | F10: 5070 | G10: =F10*Formula!B2 -> 808665
A11: - | B11: - | C11: - | D11: Bank of India | E11: =F11*Formula!B3 -> 8534955.8 | F11: 90991 | G11: =F11*Formula!B2 -> 14513064
A12: - | B12: - | C12: - | D12: Bank of India | E12: =F12*Formula!B3 -> 220523.8 | F12: 2351 | G12: =F12*Formula!B2 -> 374984.5
A13: - | B13: - | C13: - | D13: HDFC Bank | E13: =F13*Formula!B3 -> 1594600 | F13: 17000 | G13: =F13*Formula!B2 -> 2711500
A14: - | B14: - | C14: - | D14: Bank of Baroda | E14: =F14*Formula!B3 -> 440015.8 | F14: 4691 | G14: =F14*Formula!B2 -> 748214.5
A15: - | B15: - | C15: - | D15: Yes Bank | E15: =F15*Formula!B3 -> 83013 | F15: 885 | G15: =F15*Formula!B2 -> 141157.5
A16: India | B16: Cash in Bank | C16: Ricardo | D16: State Bank of India NRE | E16: 10280 | F16: =E16/Formula!B3 -> 109.59488 | G16: =F16*Formula!B2 -> 17480.384
A17: - | B17: - | C17: - | D17: State Bank of India NRO | E17: 10000 | F17: =E17/Formula!B3 -> 106.60981 | G17: =F17*Formula!B2 -> 17004.264
A18: - | B18: - | C18: - | D18: Bank of India NRE | E18: 385004 | F18: =E18/Formula!B3 -> 4104.5203 | G18: =F18*Formula!B2 -> 654670.98
A19: - | B19: - | C19: - | D19: Bank of India NRO | E19: 2141703 | F19: =E19/Formula!B3 -> 22832.655 | G19: =F19*Formula!B2 -> 3641808.4
A20: - | B20: - | C20: - | D20: ICICI Bank NRO | E20: =3637285+963533 -> 4600818 | F20: =E20/Formula!B3 -> 49049.232 | G20: =F20*Formula!B2 -> 7823352.6
A21: - | B21: - | C21: - | D21: Bank of Baroda NRO | E21: 30000 | F21: =E21/Formula!B3 -> 319.82942 | G21: =F21*Formula!B2 -> 51012.793
A22: - | B22: - | C22: - | D22: HDFC Bank NRE | E22: 10000 | F22: =E22/Formula!B3 -> 106.60981 | G22: =F22*Formula!B2 -> 17004.264
A23: - | B23: - | C23: - | D23: HDFC Bank NRO | E23: 10000 | F23: =E23/Formula!B3 -> 106.60981 | G23: =F23*Formula!B2 -> 17004.264
A24: - | B24: - | C24: - | D24: Yes Bank NRE | E24: 83000 | F24: =E24/Formula!B3 -> 884.86141 | G24: =F24*Formula!B2 -> 141135.39
A25: - | B25: - | C25: - | D25: Yes Bank NRO | E25: 10000 | F25: =E25/Formula!B3 -> 106.60981 | G25: =F25*Formula!B2 -> 17004.264
A26: - | B26: - | C26: - | D26: Shriram FD | E26: 500000 | F26: =E26/Formula!B3 -> 5330.4904 | G26: =F26*Formula!B2 -> 850213.22
A27: India | B27: Cash in Bank | C27: Veronica | D27: State Bank of India | E27: 0 | F27: =E27/Formula!B3 -> 0 | G27: =F27*Formula!B2 -> 0
A28: - | B28: - | C28: - | D28: ICICI Bank | E28: 755193 | F28: =E28/Formula!B3 -> 8051.0981 | G28: =F28*Formula!B2 -> 1284150.1
A29: - | B29: - | C29: - | D29: Bank of Baroda | E29: 152000 | F29: =E29/Formula!B3 -> 1620.4691 | G29: =F29*Formula!B2 -> 258464.82
A30: - | B30: - | C30: - | D30: Punjab National | E30: 0 | F30: =E30/Formula!B3 -> 0 | G30: =F30*Formula!B2 -> 0
A31: - | B31: - | C31: - | D31: Post Office | E31: 0 | F31: =E31/Formula!B3 -> 0 | G31: =F31*Formula!B2 -> 0
A32: India | B32: Cash in Bank | C32: Bong | D32: State Bank of India | E32: 160000 | F32: =E32/Formula!B3 -> 1705.7569 | G32: =F32*Formula!B2 -> 272068.23
A33: - | B33: - | C33: Paul | D33: Yes Bank | E33: 0 | F33: =E33/Formula!B3 -> 0 | G33: =F33*Formula!B2 -> 0
A34: India | B34: Cash Loans given to Family | C34: Ricardo | D34: Sabrina | E34: 1057500 | F34: =E34/Formula!B3 -> 11273.987 | G34: =E34*Formula!B4 -> 1797750
A35: - | B35: - | C35: - | D35: Julian | E35: 332000 | F35: =E35/Formula!B3 -> 3539.4456 | G35: =E35*Formula!B4 -> 564400
A36: - | B36: - | C36: - | D36: Subuhi | E36: 898000 | F36: =E36/Formula!B3 -> 9573.5608 | G36: =E36*Formula!B4 -> 1526600
A37: - | B37: - | C37: - | D37: Jagdish | E37: 1200000 | F37: =E37/Formula!B3 -> 12793.177 | G37: =E37*Formula!B4 -> 2040000
A38: India | B38: Stocks | C38: Ricardo | D38: Finolex Industries | E38: 79045 | F38: =E38/Formula!B3 -> 842.69723 | G38: =E38*Formula!B4 -> 134376.5
A39: - | B39: - | C39: - | D39: Hindustan Foods | E39: 243475 | F39: =E39/Formula!B3 -> 2595.6823 | G39: =E39*Formula!B4 -> 413907.5
A40: - | B40: - | C40: - | D40: NCL Industries | E40: 68360 | F40: =E40/Formula!B3 -> 728.78465 | G40: =E40*Formula!B4 -> 116212
A41: India | B41: Vernonica Portfolio | C41: Veronica | D41: Stocks | E41: 85433 | F41: =E41/Formula!B3 -> 910.79957 | G41: =E41*Formula!B4 -> 145236.1
A42: - | B42: - | C42: - | D42: Fixed Deposits | E42: 9692378 | F42: =E42/Formula!B3 -> 103330.26 | G42: =E42*Formula!B4 -> 16477043
A43: India | B43: Gold (Physical) | C43: Ricardo | D43: 10.5 grams gold | E43: =10.5*14280 -> 149940 | F43: =E43/Formula!B3 -> 1598.5075 | G43: =E43*Formula!B4 -> 254898
A44: - | B44: - | C44: - | D44: 14.83 grams gold | E44: =14.83*14280 -> 211772.4 | F44: =E44/Formula!B3 -> 2257.7015 | G44: =E44*Formula!B4 -> 360013.08
A45: Japan | B45: Real estate (Capital Repayment) | C45: Ricardo | D45: Ober Grandious | E45: =G45/Formula!B4 -> 7518429.4 | F45: =G45/Formula!B2 -> 80133.73 | G45: 12781330
A46: - | B46: - | C46: - | D46: Phoenix Waseda | E46: =G46/Formula!B4 -> 2000441.2 | F46: =G46/Formula!B2 -> 21321.317 | G46: 3400750
A47: - | B47: - | C47: - | D47: Urban Hills Waseda | E47: =G47/Formula!B4 -> 1736717.6 | F47: =G47/Formula!B2 -> 18510.47 | G47: 2952420
A48: - | B48: - | C48: - | D48: Lions Plaza Hakusan | E48: =G48/Formula!B4 -> 1259277.6 | F48: =G48/Formula!B2 -> 13421.768 | G48: 2140772
A49: - | B49: - | C49: - | D49: Castle mansion | E49: =G49/Formula!B4 -> 1349653.5 | F49: =G49/Formula!B2 -> 14385.022 | G49: 2294411
A50: Japan | B50: Real estate (Unrealized Profit) | C50: Ricardo | D50: Ober Grandious | E50: =G50/Formula!B4 -> 6705882.4 | F50: =G50/Formula!B2 -> 71473.354 | G50: ='Global Assets -old'!F23 -> 11400000
A51: - | B51: - | C51: - | D51: Phoenix Waseda | E51: =G51/Formula!B4 -> 2647058.8 | F51: =G51/Formula!B2 -> 28213.166 | G51: ='Global Assets -old'!F24 -> 4500000
A52: - | B52: - | C52: - | D52: Urban Hills Waseda | E52: =G52/Formula!B4 -> 2382352.9 | F52: =G52/Formula!B2 -> 25391.85 | G52: ='Global Assets -old'!F25 -> 4050000
A53: - | B53: - | C53: - | D53: Lions Plaza Hakusan | E53: =G53/Formula!B4 -> 1941176.5 | F53: =G53/Formula!B2 -> 20689.655 | G53: ='Global Assets -old'!F26 -> 3300000
A54: - | B54: - | C54: - | D54: Castle mansion | E54: =G54/Formula!B4 -> 2382352.9 | F54: =G54/Formula!B2 -> 25391.85 | G54: ='Global Assets -old'!F27 -> 4050000
A55: Japan | B55: Cash in Bank | C55: Ricardo | D55: Shinsei | E55: =G55/Formula!B4 -> 1358707.6 | F55: =G55/Formula!B2 -> 14481.524 | G55: 2309803
A56: - | B56: - | C56: - | D56: Post Office | E56: =G56/Formula!B4 -> 411601.18 | F56: =G56/Formula!B2 -> 4386.9718 | G56: 699722
A57: - | B57: - | C57: - | D57: 7-Eleven | E57: =G57/Formula!B4 -> 117828.24 | F57: =G57/Formula!B2 -> 1255.8495 | G57: 200308
A58: - | B58: - | C58: - | D58: MUFJ | E58: =G58/Formula!B4 -> 117755.88 | F58: =G58/Formula!B2 -> 1255.0784 | G58: 200185
A59: - | B59: - | C59: - | D59: Mizuho | E59: =G59/Formula!B4 -> 118048.24 | F59: =G59/Formula!B2 -> 1258.1944 | G59: 200682
A60: - | B60: - | C60: - | D60: SMBC | E60: =G60/Formula!B4 -> 29681.176 | F60: =G60/Formula!B2 -> 316.3511 | G60: 50458
A61: - | B61: - | C61: - | D61: Japan Netto | E61: =G61/Formula!B4 -> 147161.76 | F61: =G61/Formula!B2 -> 1568.4953 | G61: 250175
A62: - | B62: - | C62: - | D62: Rakuten | E62: =G62/Formula!B4 -> 117832.94 | F62: =G62/Formula!B2 -> 1255.8997 | G62: 200316
A63: Japan | B63: Cash in Bank | C63: Kaori | D63: Mizuho | E63: =G63/Formula!B4 -> 1149484.7 | F63: =G63/Formula!B2 -> 12251.561 | G63: 1954124
A64: - | B64: - | C64: - | D64: MUFJ | E64: =G64/Formula!B4 -> 238652.94 | F64: =G64/Formula!B2 -> 2543.6364 | G64: 405710
A65: - | B65: - | C65: - | D65: Post Office | E65: =G65/Formula!B4 -> 171121.76 | F65: =G65/Formula!B2 -> 1823.8683 | G65: 290907
A66: - | B66: - | C66: - | D66: Shinsei | E66: =G66/Formula!B4 -> 264888.24 | F66: =G66/Formula!B2 -> 2823.2602 | G66: 450310
A67: - | B67: - | C67: - | D67: Rakuten | E67: =G67/Formula!B4 -> 23529.412 | F67: =G67/Formula!B2 -> 250.7837 | G67: 40000
A68: Japan | B68: Cash in Envelope | C68: Kaori | D68: AU Pay Suica | E68: =G68/Formula!B4 -> 352941.18 | F68: =G68/Formula!B2 -> 3761.7555 | G68: 600000
A69: - | B69: - | C69: - | D69: Nenkin Kenkohoken | E69: =G69/Formula!B4 -> 205882.35 | F69: =G69/Formula!B2 -> 2194.3574 | G69: 350000
A70: - | B70: - | C70: - | D70: Minimaid Travel | E70: =G70/Formula!B4 -> 111764.71 | F70: =G70/Formula!B2 -> 1191.2226 | G70: 190000
A71: - | B71: - | C71: - | D71: Kotei Shisanzei | E71: =G71/Formula!B4 -> 152941.18 | F71: =G71/Formula!B2 -> 1630.094 | G71: 260000
A72: - | B72: - | C72: - | D72: Kaatsu Pilates | E72: =G72/Formula!B4 -> 170588.24 | F72: =G72/Formula!B2 -> 1818.1818 | G72: 290000
A73: - | B73: - | C73: - | D73: Okozukai | E73: =G73/Formula!B4 -> 58823.529 | F73: =G73/Formula!B2 -> 626.95925 | G73: 100000
A74: - | B74: - | C74: - | D74: Undecided | E74: =G74/Formula!B4 -> 205882.35 | F74: =G74/Formula!B2 -> 2194.3574 | G74: 350000
A75: Japan | B75: Gold (Physical) | C75: Kaori | D75: Tanaka K.K | E75: =G75*Formula!B4 -> 76500 | F75: =G75/Formula!B2 -> 282.13166 | G75: 45000
A76: - | B76: - | C76: Ricardo | D76: Tanaka K.K | E76: 76500 | F76: 282 | G76: 45000
A77: Japan | B77: Japanese Nenkin Pension | C77: Ricardo | D77: Ricardo Pension | E77: =G77*Formula!B4 -> 16466800 | F77: =G77/Formula!B2 -> 60729.486 | G77: 9686353
A78: - | B78: - | C78: Kaori | D78: Kaori Pension | E78: =G78*Formula!B4 -> 6364563.7 | F78: =G78/Formula!B2 -> 23472.483 | G78: 3743861
A79: Japan | B79: Ideco Private Pension | C79: Ricardo | D79: Ricardo Pension | E79: =G79*Formula!B4 -> 4009178 | F79: =G79/Formula!B2 -> 14785.831 | G79: 2358340
A80: - | B80: - | C80: Kaori | D80: Kaori Pension | E80: =G80*Formula!B4 -> 3146098.2 | F80: =G80/Formula!B2 -> 11602.796 | G80: 1850646
A81: Japan | B81: Stocks | C81: Ricardo | D81: SBI Securities | E81: =F81*Formula!B3 -> 5543204.8 | F81: =22760+36336 -> 59096 | G81: =F81*Formula!B2 -> 9425812
A82: - | B82: - | C82: Kaori | D82: SBI, Rakuten Securities | E82: =F82*Formula!B3 -> 5040343 | F82: =23046+23046+7643 -> 53735 | G82: =F82*Formula!B2 -> 8570732.5
A83: No Region | B83: Cryptocurrency | C83: Ricardo | D83: Bitcoin | E83: =F83*Formula!B3 -> 5558869.4 | F83: 59263 | G83: =F83*Formula!B2 -> 9452448.5
A84: - | B84: - | C84: - | D84: Stablecoins | E84: =F84*Formula!B3 -> 864060.27 | F84: ='Global Assets -old'!H194+'Global Assets -old'!H195+'Global Assets -old'!H197+'Global Assets -old'!H199+-'Global Assets -old'!H200+'Global Assets -old'!H202+'Global Assets -old'!H203+'Global Assets -old'!H204+'Global Assets -old'!H205+'Global Assets -old'!H206+'Global Assets -old'!H208+'Global Assets -old'!H209 -> 9211.73 | G84: =F84*Formula!B2 -> 1469270.9
A85: - | B85: - | C85: - | D85: Altcoins | E85: =F85*Formula!B3 -> 594027.9 | F85: ='Global Assets -old'!H196+'Global Assets -old'!H211+1008 -> 6332.92 | G85: =F85*Formula!B2 -> 1010100.7
A86: Europe | B86: Cash in Overseas Bank | C86: Ricardo | D86: Ziraat Bank | E86: =F86*Formula!B3 -> 187600 | F86: 2000 | G86: =F86*Formula!B2 -> 319000
A87: - | B87: - | C87: - | D87: TBC | E87: =F87*Formula!B3 -> 46900 | F87: 500 | G87: =F87*Formula!B2 -> 79750
A88: Global | B88: Summary | C88: System | D88: Total Assets | E88: =SUM(E3:E87) -> 1.8353897e+08 | F88: =SUM(F3:F87) -> 1746447.3 | G88: =SUM(G3:G87) -> 2.7853596e+08

Sheet Formula
A2: 1 USD | B2: 159.5 | C2: JPY
A3: 1 USD | B3: 93.8 | C3: INR
A4: 1 INR | B4: 1.7 | C4: JPY

Sheet Global Assets -old
A1: As on 22-4-2026
B2: Real estate | I2: 1 USD | J2: 159.5 | K2: JPY
B3: India | I3: 1 USD | J3: 93.8 | K3: INR
B4: Current Sale Price | C4: Flat | D4: INR | E4: JPY | F4: USD | I4: 1 INR | J4: 1.7 | K4: JPY
C5: Poonam Residency | D5: 10500000 | E5: =D5*J4 -> 17850000 | F5: =D5/J3 -> 111940.3
C6: Sunway Megapolis | D6: 8500000 | E6: =D6*J4 -> 14450000 | F6: =D6/J3 -> 90618.337
C7: Osia Maple Leaf | D7: 7500000 | E7: =D7*J4 -> 12750000 | F7: =D7/J3 -> 79957.356
C8: Venusta Classic | D8: 5500000 | E8: =D8*J4 -> 9350000 | F8: =D8/J3 -> 58635.394
C9: Altamonte | D9: 4500000 | E9: =D9*J4 -> 7650000 | F9: =D9/J3 -> 47974.414
C10: Osia Arcade | D10: 2000000 | E10: =D10*J4 -> 3400000 | F10: =D10/J3 -> 21321.962
C11: Total | D11: =SUM(D5:D10) -> 38500000 | E11: =SUM(E5:E10) -> 65450000 | F11: =SUM(F5:F10) -> 410447.76
B13: Japan
B14: Capital repayment | C14: Flat | D14: JPY | E14: INR | F14: USD | G14: Purchase Amt JPY
C15: Ober Grandious | D15: 12781330 | E15: =D15/J4 -> 7518429.4 | F15: =D15/J2 -> 80133.73 | G15: 38000000
C16: Phoenix Waseda | D16: 3400750 | E16: =D16/J4 -> 2000441.2 | F16: =D16/J2 -> 21321.317 | G16: 15000000
C17: Urban Hills Waseda | D17: 2952420 | E17: =D17/J4 -> 1736717.6 | F17: =D17/J2 -> 18510.47 | G17: 13500000
C18: Lions Plaza Hakusan | D18: 2140772 | E18: =D18/J4 -> 1259277.6 | F18: =D18/J2 -> 13421.768 | G18: 11000000
C19: Castle mansion | D19: 2294411 | E19: =D19/J4 -> 1349653.5 | F19: =D19/J2 -> 14385.022 | G19: 13500000
C20: Total | D20: =SUM(D14:D19) -> 23569683 | E20: =SUM(E14:E19) -> 13864519 | F20: =SUM(F14:F19) -> 147772.31 | G20: =SUM(G14:G19) -> 91000000 | H20: =G20-D20 -> 67430317
B22: Current Sale Price | C22: Flat | D22: Purchase Price JPY | E22: Sale Price JPY | F22: Unrealized Profit JPY | G22: INR | H22: USD
C23: Ober Grandious | D23: 38000000 | E23: =D23*0.3 + D23 -> 49400000 | F23: =E23-D23 -> 11400000 | G23: =F23*J4 -> 19380000 | H23: =F23/J3 -> 121535.18
C24: Phoenix Waseda | D24: 15000000 | E24: =D24*0.3 + D24 -> 19500000 | F24: =E24-D24 -> 4500000 | G24: =F24*J4 -> 7650000 | H24: =F24/J3 -> 47974.414
C25: Urban Hills Waseda | D25: 13500000 | E25: =D25*0.3 + D25 -> 17550000 | F25: =E25-D25 -> 4050000 | G25: =F25*J4 -> 6885000 | H25: =F25/J3 -> 43176.972
C26: Lions Plaza Hakusan | D26: 11000000 | E26: =D26*0.3 + D26 -> 14300000 | F26: =E26-D26 -> 3300000 | G26: =F26*J4 -> 5610000 | H26: =F26/J3 -> 35181.237
C27: Castle mansion | D27: 13500000 | E27: =D27*0.3 + D27 -> 17550000 | F27: =E27-D27 -> 4050000 | G27: =F27*J4 -> 6885000 | H27: =F27/J3 -> 43176.972
C28: Total | D28: =SUM(D23:D27) -> 91000000 | E28: =SUM(E23:E27) -> 118300000 | F28: =SUM(F23:F27) -> 27300000 | G28: =SUM(G23:G27) -> 46410000 | H28: =SUM(H23:H27) -> 291044.78
B31: Capital repayment + Unrealized Profit
C32: Flat | D32: Profit JPY | E32: INR | F32: USD
C33: Ober Grandious | D33: =F23+D15 -> 24181330 | E33: =D33/J4 -> 14224312 | F33: =E33/J3 -> 151645.11
C34: Phoenix Waseda | D34: =F24+D16 -> 7900750 | E34: =D34/J4 -> 4647500 | F34: =E34/J3 -> 49546.908
C35: Urban Hills Waseda | D35: =F25+D17 -> 7002420 | E35: =D35/J4 -> 4119070.6 | F35: =E35/J3 -> 43913.332
C36: Lions Plaza Hakusan | D36: =F26+D18 -> 5440772 | E36: =D36/J4 -> 3200454.1 | F36: =E36/J3 -> 34119.98
C37: Castle mansion | D37: =F27+D19 -> 6344411 | E37: =D37/J4 -> 3732006.5 | F37: =E37/J3 -> 39786.849
C38: Total | D38: =SUM(D33:D37) -> 50869683 | E38: =SUM(E33:E37) -> 29923343 | F38: =SUM(F33:F37) -> 319012.18
B42: Cash
B43: India
C44: Fixed Deposits
D45: Bank | E45: USD | F45: INR | G45: JPY
D46: State Bank of India | E46: 292018 | F46: =E46*J3 -> 27391288 | G46: =E46*J2 -> 46576871
D47: State Bank of India | E47: 5070 | F47: =E47*J3 -> 475566 | G47: =E47*J2 -> 808665
D48: Bank of India | E48: 90991 | F48: =E48*J3 -> 8534955.8 | G48: =E48*J2 -> 14513064
D49: Bank of India | E49: 2351 | F49: =E49*J3 -> 220523.8 | G49: =E49*J2 -> 374984.5
D50: HDFC Bank | E50: 17000 | F50: =E50*J3 -> 1594600 | G50: =E50*J2 -> 2711500
D51: Bank of Baroda | E51: =F51/J3 -> 4691.0021 | F51: 440016 | G51: =E51*J2 -> 748214.84
D52: Yes Bank | E52: =F52/J3 -> 885 | F52: 83013 | G52: =E52*J2 -> 141157.5
D53: Total | E53: =SUM(E46:E52) -> 413006 | F53: =SUM(F46:F52) -> 38739963 | G53: =SUM(G46:G52) -> 65874457
B56: Cash in Hand
C57: Bank | D57: NRE INR | E57: NRO INR | F57: NRO + NRE INR | G57: JPY | H57: USD
B58: Ricardo | C58: State Bank of India | D58: 10280 | E58: 510255 | F58: =D58+E58 -> 520535 | G58: =F58*J4 -> 884909.5 | H58: =G58/J2 -> 5548.0219
C59: Bank of India | D59: 5004 | E59: 2141703 | F59: =D59+E59 -> 2146707 | G59: =F59*J4 -> 3649401.9 | H59: =G59/J2 -> 22880.263
C60: ICICI Bank | D60: 0 | E60: 3940478 | F60: =D60+E60 -> 3940478 | G60: =F60*J4 -> 6698812.6 | H60: =G60/J2 -> 41998.825
C61: Bank of Baroda | D61: 0 | E61: 30000 | F61: =D61+E61 -> 30000 | G61: =F61*J4 -> 51000 | H61: =G61/J2 -> 319.74922
C62: HDFC Bank | D62: 0 | E62: 15000 | F62: =D62+E62 -> 15000 | G62: =F62*J4 -> 25500 | H62: =G62/J2 -> 159.87461
C63: Yes Bank | D63: 10000 | E63: 10000 | F63: =D63+E63 -> 20000 | G63: =F63*J4 -> 34000 | H63: =G63/J2 -> 213.16614
C64: Total | D64: =SUM(D58:D63) -> 25284 | E64: =SUM(E58:E63) -> 6647436 | F64: =SUM(F58:F63) -> 6672720 | G64: =SUM(G58:G63) -> 11343624 | H64: =SUM(H58:H63) -> 71119.9
D65: INR | E65: JPY | F65: USD
B66: Mom | C66: State Bank of India | D66: 0 | E66: =D66*J4 -> 0 | F66: =E66/J2 -> 0
C67: ICICI Bank | D67: 755193 | E67: =D67*J4 -> 1283828.1 | F67: =E67/J2 -> 8049.079
C68: Bank of Baroda | D68: 152000 | E68: =D68*J4 -> 258400 | F68: =E68/J2 -> 1620.0627
C69: Punjab National | D69: 0 | E69: =D69*J4 -> 0 | F69: =E69/J2 -> 0
C70: Post Office | D70: 0 | E70: =D70*J4 -> 0 | F70: =E70/J2 -> 0
C71: Total | D71: =SUM(D66:D70) -> 907193 | E71: =SUM(E66:E70) -> 1542228.1 | F71: =SUM(F66:F70) -> 9669.1417
D73: INR | E73: JPY | F73: USD
B74: Bong | C74: ICICI Bank | D74: 160000 | E74: =D74*J4 -> 272000 | F74: =D74/J3 -> 1705.7569
C75: Total | D75: =D74 -> 160000 | E75: =E74 -> 272000 | F75: =F74 -> 1705.7569
D77: INR | E77: JPY | F77: USD
B78: Paul | C78: Yes Bank | D78: 0 | E78: =D78*J4 -> 0 | F78: =D78/J3 -> 0
C79: Total | D79: =D78 -> 0 | E79: =E78 -> 0 | F79: =F78 -> 0
B81: Grand Total India | D81: INR | E81: JPY | F81: USD
D82: =F53+F64+D71+D75+D79 -> 46479876 | E82: =G53+G64+E71+E75+E79 -> 79032309 | F82: =E53+H64+F71+F75+F79 -> 495500.8
C89: Japan
D90: Cash in Hand and Bank
E91: Bank | F91: JPY | G91: INR | H91: USD
D92: Ricardo | E92: Shinsei | F92: 2309803 | G92: =F92/J4 -> 1358707.6 | H92: =F92/J2 -> 14481.524
E93: Post Office | F93: 699722 | G93: =F93/J4 -> 411601.18 | H93: =F93/J2 -> 4386.9718
E94: 7-Eleven | F94: 200308 | G94: =F94/J4 -> 117828.24 | H94: =F94/J2 -> 1255.8495
E95: MUFJ | F95: 200185 | G95: =F95/J4 -> 117755.88 | H95: =F95/J2 -> 1255.0784
E96: Mizuho | F96: 200682 | G96: =F96/J4 -> 118048.24 | H96: =F96/J2 -> 1258.1944
E97: SMBC | F97: 50458 | G97: =F97/J4 -> 29681.176 | H97: =F97/J2 -> 316.3511
E98: Japan Netto | F98: 250175 | G98: =F98/J4 -> 147161.76 | H98: =F98/J2 -> 1568.4953
E99: Rakuten | F99: 200316 | G99: =F99/J4 -> 117832.94 | H99: =F99/J2 -> 1255.8997
E100: Total | F100: =SUM(F92:F99) -> 4111649 | G100: =SUM(G92:G99) -> 2418617.1 | H100: =SUM(H92:H99) -> 25778.364
E102: Bank | F102: JPY | G102: INR | H102: USD
D103: Kaori | E103: Mizuho | F103: 1954124 | G103: =F103/J4 -> 1149484.7 | H103: =F103/J2 -> 12251.561
E104: MUFJ | F104: 405710 | G104: =F104/J4 -> 238652.94 | H104: =F104/J2 -> 2543.6364
E105: Post Office | F105: 290907 | G105: =F105/J4 -> 171121.76 | H105: =F105/J2 -> 1823.8683
E106: Shinsei | F106: 450310 | G106: =F106/J4 -> 264888.24 | H106: =F106/J2 -> 2823.2602
E107: Rakuten | F107: 40000 | G107: =F107/J4 -> 23529.412 | H107: =F107/J2 -> 250.7837
E108: Total | F108: =SUM(F103:F107) -> 3141051 | G108: =SUM(G103:G107) -> 1847677.1 | H108: =SUM(H103:H107) -> 19693.11
E110: Expenses | F110: JPY | G110: INR | H110: USD
D111: Cash in Envelope 2026 | E111: AU Pay Suica | F111: 600000 | G111: =F111/J4 -> 352941.18 | H111: =F111/J2 -> 3761.7555
E112: Nenkin Kenkohoken | F112: 350000 | G112: =F112/J4 -> 205882.35 | H112: =F112/J2 -> 2194.3574
E113: Minimaid Travel | F113: 190000 | G113: =F113/J4 -> 111764.71 | H113: =F113/J2 -> 1191.2226
E114: Kotei Shisanzei | F114: 260000 | G114: =F114/J4 -> 152941.18 | H114: =F114/J2 -> 1630.094
E115: Kaatsu Pilates | F115: 290000 | G115: =F115/J4 -> 170588.24 | H115: =F115/J2 -> 1818.1818
E116: Okozukai | F116: 100000 | G116: =F116/J4 -> 58823.529 | H116: =F116/J2 -> 626.95925
E117: Total | F117: =SUM(F111:F116) -> 1790000 | G117: =SUM(G111:G116) -> 1052941.2 | H117: =SUM(H111:H116) -> 11222.571
E119: Expenses | F119: JPY | G119: INR | H119: USD
D120: Cash in Envelope 2027 | E120: Not decided | F120: 350000 | G120: =F120/J4 -> 205882.35 | H120: =F120/J2 -> 2194.3574
E121: Total | F121: =SUM(F120:F120) -> 350000 | G121: =SUM(G120:G120) -> 205882.35 | H121: =SUM(H120:H120) -> 2194.3574
...

Sheet Sheet1
B2: Analysis of Global Assets
B5: ✅ 1. REAL ESTATE — TOTAL
B7: India
B9: Already totaled:
B10: INR 38,500,000
B11: JPY 65,450,000
B12: USD 410,448
B14: Japan (Capital + Unrealized Profit)
B16: Already totaled:
B17: JPY 50,869,683
B18: INR 29,923,343
B19: USD 319,012
B21: 🔹 REAL ESTATE — GRAND TOTAL
B23: Currency | C23: Amount
B24: INR | C24: 68423343
B25: JPY | C25: 116319683
B26: USD | C26: 729460
B29: ✅ 2. CASH — TOTAL
B31: You’ve already given:
B33: India Cash Grand Total
B35: INR 45,286,041
B36: JPY 76,959,287.60
B37: USD 482,504
B39: Japan Cash Grand Total
B41: JPY 7,252,700
B42: INR 4,266,294
B43: USD 45,471
B45: Less: Japan Expenses 2026 + 2027
B47: (1,790,000 + 350,000 = 2,140,000 JPY)
... B62: 🔹 CASH — GRAND TOTAL
B64: Currency | C64: Amount
B65: INR | C65: 48293512
B66: JPY | C66: 82071988
B67: USD | C67: 514558
B70: ✅ 3. PASSIVE INCOME (India Loans + Shriram)
B72: Given:
B73: INR 67,500
B74: JPY 114,750
B75: USD 750
B79: ✅ 4. GOLD + TANAKA + STAMPS + NENKIN
B81: Physical Gold
B83: INR: 361,712
B84: JPY: 614,911
B85: USD: 3,856
B87: Tanaka Gold
B89: JPY: 90,304
... B105: 🔹 TOTAL (Gold + Tanaka + Stamps + Nenkin)
B107: Currency | C107: Amount
B108: INR | C108: 9814958
B109: JPY | C109: 16690125
B110: USD | C110: 104615
B113: ✅ 5. STOCKS
B115: iDeCo Japan
B117: JPY: 4,208,986
B118: INR: 2,475,874
B119: USD: 26,389
B121: India Physical Stocks
B123: INR: 390,880
B124: JPY: 664,496
B125: USD: 2,451
B127: Mom’s Portfolio
B129: INR: 9,777,811
B130: JPY: 16,622,279
... B143: 🔹 TOTAL STOCKS
B145: Currency | C145: Amount
B146: INR | C146: 22894098
B147: JPY | C147: 38918768
B148: USD | C148: 242266
B151: ✅ 6. CRYPTO
B153: Already listed:
B154: USD 68,739
B156: INR ≈ 6,447,778
B157: JPY ≈ 10,960,000
B161: 🌟🌟 FINAL GRAND TOTAL (ALL ASSETS) 🌟🌟
B163: Now sum all categories.
B167: ✅ TOTAL NET WORTH — INR
B169: Category | C169: INR
B170: Real estate | C170: 68423343
B171: Cash | C171: 48293512
B172: Passive income | C172: 67500
B173: Gold + Stamps + Nenkin | C173: 9814958
B174: Stocks | C174: 22894098
B175: Crypto | C175: 6447778
B176: TOTAL INR | C176: =C193*#REF! -> #REF!
B178: ⭐ ₹15.78 crore
B180: (= approx ₹15.78 crore)
B184: ✅ TOTAL NET WORTH — USD
B186: Category | C186: USD
B187: Real estate | C187: 729460
B188: Cash | C188: 514558
B189: Passive income | C189: 750
B190: Gold + Stamps + Nenkin | C190: 104615
B191: Stocks | C191: 242266
B192: Crypto | C192: 68739
B193: TOTAL USD | C193: 1682388
B195: ⭐ ≈ $1.66 Million
B199: ✅ TOTAL NET WORTH — JPY
B201: Category | C201: JPY
B202: Real estate | C202: 116319683
B203: Cash | C203: 82071987
...

Sheet USD to INR Forecast
B2: USD to INR Forecast
B4: https://capex.com/en/overview/usd-to-inr-forecast
B5: https://www.bankbazaar.com/currency-exchange/historical-value-of-1-usd-in-inr.html
B6: Factors that have led to the depreciation of Indian Rupees with respect to the US dollar
B8: Given below are the reasons due to which INR has depreciated with respect to USD:
B10: After India attained its independence in 1947, the Indian Rupee started to be compared to the US dollar. Since there were no credits or debits on the national balance sheet, Re.1 could then be regarded as equal to $1. However, the British pound where £1 was equal to Rs.13 served as the basis for the value of Indian currency, it played a role in the depreciation of the rupee. Furthermore, this pricing of rupee versus the British pound persisted because there was no accepted method of currency comparison until 1944.
B11: The value of the Indian Rupee back in 1947 was 4.76 and stayed consistent till 1966. However, since 1950, the economy of India witnessed a decline, which was due to the country’s credit standing on the global market. Apart from that, the 1962 India-China war, the subsequent India-Pakistan war in 1965, and the 1966 drought all contributed to the situation's deterioration. By 1967, all of them had changed the currency rate from $1 to Rs.7.50.
B12: The value of the rupee also suffered in 1974 as its value fell to 8.10 due to the oil shock in 1973 when OAPEC or the Organisation of Arab Petroleum Exporting Countries decided to reduce proportion. India had to borrow foreign currency to deal with the situation and the ensuing political turmoil. The value of the Indian currency decreased as a result. The exchange rate declined during the course of the 1980s, peaking at 17.50 in the 1990s, down from $1 USD to Rs.7.50 in 1967.
B13: India’s economy suffered back in 1990 as the fiscal deficit decreased by 7.8% of the GDP and India was on the verge of being branded a defaulter in the Indian market. This had a significant impact on the value of the rupee. India had to make their export cheaper and import dearer.
B14: The economic crisis in 1990 played a role in 1992 when the rupee devalued and the exchange rate came to S1 equal to Rs.25.92. Since then, the value of the Indian rupee has started to decline, and it is currently worth Rs.74.57. The dollar price was Rs.45.32 in 2004 and rose to Rs.62.33 over the following ten years. The highest rate of Dollar to rupee ever was recorded in February of 2016, totalling Rs.68.80.
B15: The value of the India rupee also gets affected due to any changes in the Indian rupee. As the value of crude oil in the global markets rises, the value of the Indian rupee drops and vice-versa. Other factors that have led to the value of the rupee depreciating is due to the withdrawal of foreign investors from the Indian markets, increase in government debts which causes the investors to lose interest, subsequently leading to inflation. These factors can cause further drop in the value of Indian rupee.
B17: Factors that Impact Exchange Rates
... B43: How can a countries Exchange rate decrease or become weak
C45: Rising Inflation
C46: Lowing of interest rate
C47: Less Foerign Direct Investment flows
C48: Increase in Trade Deficit or Decrease in Trade Surplus (Imports > Exports)
C49: War or Political Instability
C50: Decrease in Umemployment
C51: Increase in Fuel prices
C52: Increase in Net Outflows out of the country
C53: Decrease in Net Inflows intothe country
C54: Decrease in Rollover rates
B56: https://capex.com/en/overview/usd-to-inr-forecast

Sheet Buy USA Stocks India
B2: https://www.businesstoday.in/markets/market-commentary/story/trading-in-us-stocks-through-nse-ifsc-starts-today-10-things-you-should-know-324575-2022-03-03
B4: Top International Mutual Funds to Invest Online in 2024 through Indian Mutual Fund
C5: https://www.smallcase.com/collections/best-international-mutual-funds/
